warzone/__init__.py
warzone/analysis.py
warzone/base.py
warzone/build.py
warzone/call_of_duty.py
warzone/document_filter.py
warzone/gun_dictionary.py
warzone/medium_posts.py
warzone/outlier.py
warzone/plot.py
warzone/plots.py
warzone/regression.py
warzone/scrape.py
warzone/squad.py
warzone/user.py
warzone_analysis-2.4.1.dist-info/LICENSE
warzone_analysis-2.4.1.dist-info/METADATA
warzone_analysis-2.4.1.dist-info/WHEEL
warzone_analysis-2.4.1.dist-info/top_level.txt
warzone_analysis-2.4.1.dist-info/RECORD
