Metadata-Version: 2.1
Name: warzone-analysis
Version: 2.4.1
Summary: Call of Duty Warzone Analysis
Home-page: https://call-of-duty-warzone-analysis.readthedocs.io/en/latest/intro.html#write-ups-and-examples
Author: Peter Rigali
Author-email: peterjrigali@gmail.com
License: MIT
Platform: UNKNOWN
License-File: LICENSE
